{
  "queryName": "DEPOSITOR",
  "rowCount": 139,
  "maxRowsLimit": "unlimited",
  "data": [
    {
      "dep_ID": 1,
      "dep_Code": "AC",
      "cmp_FullName": "cmp_FullName4947",
      "cmp_Address": "\u05D4\u05E9\u05E8\u05D5\u05DF 3 \u05E7\u05E8\u05D9\u05D9\u05EA \u05E9\u05D3\u05D4 \u05D4\u05EA\u05E2\u05D5\u05E4\u05D4",
      "cmp_City": "\u05DC\u05D5\u05D3",
      "cmp_ZipCode": null,
      "cmp_Phone": "Phone4947",
      "cmp_Responsible": "cmp_Responsible4947",
      "cmp_Fax": null,
      "cmp_AFM": "99999",
      "cmp_DUNSNumber": null,
      "cmp_LastUpdateTime": "2022-11-02T11:58:18.7370000"
    },
    {
      "dep_ID": 3,
      "dep_Code": "HD",
      "cmp_FullName": "cmp_FullName4949",
      "cmp_Address": null,
      "cmp_City": null,
      "cmp_ZipCode": null,
      "cmp_Phone": "Phone4949",
      "cmp_Responsible": "cmp_Responsible4949",
      "cmp_Fax": null,
      "cmp_AFM": null,
      "cmp_DUNSNumber": null,
      "cmp_LastUpdateTime": "2022-11-02T15:11:04.3270000"
    },
    {
      "dep_ID": 9,
      "dep_Code": "DH",
      "cmp_FullName": "cmp_FullName4952",
      "cmp_Address": null,
      "cmp_City": null,
      "cmp_ZipCode": null,
      "cmp_Phone": "Phone4952",
      "cmp_Responsible": "cmp_Responsible4952",
      "cmp_Fax": null,
      "cmp_AFM": null,
      "cmp_DUNSNumber": null,
      "cmp_LastUpdateTime": null
    },
    {
      "dep_ID": 4,
      "dep_Code": "CL",
      "cmp_FullName": "cmp_FullName4953",
      "cmp_Address": "\u05D8\u05E1\u05D8",
      "cmp_City": null,
      "cmp_ZipCode": null,
      "cmp_Phone": "Phone4953",
      "cmp_Responsible": "cmp_Responsible4953",
      "cmp_Fax": null,
      "cmp_AFM": null,
      "cmp_DUNSNumber": null,
      "cmp_LastUpdateTime": "2022-11-02T15:14:04.6230000"
    },
    {
      "dep_ID": 5,
      "dep_Code": "SG",
      "cmp_FullName": "cmp_FullName4961",
      "cmp_Address": null,
      "cmp_City": null,
      "cmp_ZipCode": null,
      "cmp_Phone": "Phone4961",
      "cmp_Responsible": "cmp_Responsible4961",
      "cmp_Fax": null,
      "cmp_AFM": null,
      "cmp_DUNSNumber": null,
      "cmp_LastUpdateTime": null
    },
    {
      "dep_ID": 6,
      "dep_Code": "TS",
      "cmp_FullName": "cmp_FullName4965",
      "cmp_Address": null,
      "cmp_City": null,
      "cmp_ZipCode": null,
      "cmp_Phone": "Phone4965",
      "cmp_Responsible": "cmp_Responsible4965",
      "cmp_Fax": null,
      "cmp_AFM": null,
      "cmp_DUNSNumber": null,
      "cmp_LastUpdateTime": null
    },
    {
      "dep_ID": 7,
      "dep_Code": "PG",
      "cmp_FullName": "cmp_FullName4966",
      "cmp_Address": null,
      "cmp_City": null,
      "cmp_ZipCode": null,
      "cmp_Phone": "Phone4966",
      "cmp_Responsible": "cmp_Responsible4966",
      "cmp_Fax": null,
      "cmp_AFM": null,
      "cmp_DUNSNumber": null,
      "cmp_LastUpdateTime": null
    },
    {
      "dep_ID": 8,
      "dep_Code": "KOL",
      "cmp_FullName": "cmp_FullName4967",
      "cmp_Address": null,
      "cmp_City": null,
      "cmp_ZipCode": null,
      "cmp_Phone": "Phone4967",
      "cmp_Responsible": "cmp_Responsible4967",
      "cmp_Fax": null,
      "cmp_AFM": null,
      "cmp_DUNSNumber": null,
      "cmp_LastUpdateTime": null
    },
    {
      "dep_ID": 10,
      "dep_Code": "LMB",
      "cmp_FullName": "cmp_FullName4968",
      "cmp_Address": null,
      "cmp_City": null,
      "cmp_ZipCode": null,
      "cmp_Phone": "Phone4968",
      "cmp_Responsible": "cmp_Responsible4968",
      "cmp_Fax": null,
      "cmp_AFM": null,
      "cmp_DUNSNumber": null,
      "cmp_LastUpdateTime": null
    },
    {
      "dep_ID": 11,
      "dep_Code": "AID",
      "cmp_FullName": "cmp_FullName4969",
      "cmp_Address": null,
      "cmp_City": null,
      "cmp_ZipCode": null,
      "cmp_Phone": "Phone4969",
      "cmp_Responsible": "cmp_Responsible4969",
      "cmp_Fax": null,
      "cmp_AFM": null,
      "cmp_DUNSNumber": null,
      "cmp_LastUpdateTime": null
    },
    {
      "dep_ID": 12,
      "dep_Code": "TOP",
      "cmp_FullName": "cmp_FullName4970",
      "cmp_Address": null,
      "cmp_City": null,
      "cmp_ZipCode": null,
      "cmp_Phone": "Phone4970",
      "cmp_Responsible": "cmp_Responsible4970",
      "cmp_Fax": null,
      "cmp_AFM": null,
      "cmp_DUNSNumber": null,
      "cmp_LastUpdateTime": null
    },
    {
      "dep_ID": 13,
      "dep_Code": "AH",
      "cmp_FullName": "cmp_FullName4971",
      "cmp_Address": null,
      "cmp_City": null,
      "cmp_ZipCode": null,
      "cmp_Phone": "Phone4971",
      "cmp_Responsible": "cmp_Responsible4971",
      "cmp_Fax": null,
      "cmp_AFM": null,
      "cmp_DUNSNumber": null,
      "cmp_LastUpdateTime": null
    },
    {
      "dep_ID": 14,
      "dep_Code": "US",
      "cmp_FullName": "cmp_FullName4972",
      "cmp_Address": null,
      "cmp_City": null,
      "cmp_ZipCode": null,
      "cmp_Phone": "Phone4972",
      "cmp_Responsible": "cmp_Responsible4972",
      "cmp_Fax": null,
      "cmp_AFM": null,
      "cmp_DUNSNumber": null,
      "cmp_LastUpdateTime": null
    },
    {
      "dep_ID": 15,
      "dep_Code": "ZK",
      "cmp_FullName": "cmp_FullName4973",
      "cmp_Address": null,
      "cmp_City": null,
      "cmp_ZipCode": null,
      "cmp_Phone": "Phone4973",
      "cmp_Responsible": "cmp_Responsible4973",
      "cmp_Fax": null,
      "cmp_AFM": null,
      "cmp_DUNSNumber": null,
      "cmp_LastUpdateTime": null
    },
    {
      "dep_ID": 16,
      "dep_Code": "NL",
      "cmp_FullName": "cmp_FullName4974",
      "cmp_Address": null,
      "cmp_City": null,
      "cmp_ZipCode": null,
      "cmp_Phone": "Phone4974",
      "cmp_Responsible": "cmp_Responsible4974",
      "cmp_Fax": null,
      "cmp_AFM": null,
      "cmp_DUNSNumber": null,
      "cmp_LastUpdateTime": null
    },
    {
      "dep_ID": 17,
      "dep_Code": "GEN",
      "cmp_FullName": "cmp_FullName4975",
      "cmp_Address": null,
      "cmp_City": null,
      "cmp_ZipCode": null,
      "cmp_Phone": "Phone4975",
      "cmp_Responsible": "cmp_Responsible4975",
      "cmp_Fax": null,
      "cmp_AFM": null,
      "cmp_DUNSNumber": null,
      "cmp_LastUpdateTime": null
    },
    {
      "dep_ID": 18,
      "dep_Code": "HAM",
      "cmp_FullName": "cmp_FullName4976",
      "cmp_Address": null,
      "cmp_City": null,
      "cmp_ZipCode": null,
      "cmp_Phone": "Phone4976",
      "cmp_Responsible": "cmp_Responsible4976",
      "cmp_Fax": null,
      "cmp_AFM": null,
      "cmp_DUNSNumber": null,
      "cmp_LastUpdateTime": null
    },
    {
      "dep_ID": 19,
      "dep_Code": "FX",
      "cmp_FullName": "cmp_FullName4977",
      "cmp_Address": "\u05DE\u05D5\u05D3\u05D9\u05E2\u05D9\u05DF ",
      "cmp_City": "\u05DE\u05D5\u05D3\u05D9\u05E2\u05D9\u05DF ",
      "cmp_ZipCode": null,
      "cmp_Phone": "Phone4977",
      "cmp_Responsible": "cmp_Responsible4977",
      "cmp_Fax": null,
      "cmp_AFM": null,
      "cmp_DUNSNumber": null,
      "cmp_LastUpdateTime": "2022-11-02T09:44:04.0370000"
    },
    {
      "dep_ID": 54,
      "dep_Code": "PRO",
      "cmp_FullName": "cmp_FullName4977",
      "cmp_Address": "\u05DE\u05D5\u05D3\u05D9\u05E2\u05D9\u05DF ",
      "cmp_City": "\u05DE\u05D5\u05D3\u05D9\u05E2\u05D9\u05DF ",
      "cmp_ZipCode": null,
      "cmp_Phone": "Phone4977",
      "cmp_Responsible": "cmp_Responsible4977",
      "cmp_Fax": null,
      "cmp_AFM": null,
      "cmp_DUNSNumber": null,
      "cmp_LastUpdateTime": "2022-11-02T09:44:04.0370000"
    },
    {
      "dep_ID": 71,
      "dep_Code": "FXN",
      "cmp_FullName": "cmp_FullName4977",
      "cmp_Address": "\u05DE\u05D5\u05D3\u05D9\u05E2\u05D9\u05DF ",
      "cmp_City": "\u05DE\u05D5\u05D3\u05D9\u05E2\u05D9\u05DF ",
      "cmp_ZipCode": null,
      "cmp_Phone": "Phone4977",
      "cmp_Responsible": "cmp_Responsible4977",
      "cmp_Fax": null,
      "cmp_AFM": null,
      "cmp_DUNSNumber": null,
      "cmp_LastUpdateTime": "2022-11-02T09:44:04.0370000"
    },
    {
      "dep_ID": 20,
      "dep_Code": "FR",
      "cmp_FullName": "cmp_FullName4978",
      "cmp_Address": null,
      "cmp_City": null,
      "cmp_ZipCode": null,
      "cmp_Phone": "Phone4978",
      "cmp_Responsible": "cmp_Responsible4978",
      "cmp_Fax": null,
      "cmp_AFM": null,
      "cmp_DUNSNumber": null,
      "cmp_LastUpdateTime": null
    },
    {
      "dep_ID": 21,
      "dep_Code": "REN",
      "cmp_FullName": "cmp_FullName4979",
      "cmp_Address": null,
      "cmp_City": null,
      "cmp_ZipCode": null,
      "cmp_Phone": "Phone4979",
      "cmp_Responsible": "cmp_Responsible4979",
      "cmp_Fax": null,
      "cmp_AFM": null,
      "cmp_DUNSNumber": null,
      "cmp_LastUpdateTime": null
    },
    {
      "dep_ID": 22,
      "dep_Code": "RT",
      "cmp_FullName": "cmp_FullName4980",
      "cmp_Address": null,
      "cmp_City": null,
      "cmp_ZipCode": null,
      "cmp_Phone": "Phone4980",
      "cmp_Responsible": "cmp_Responsible4980",
      "cmp_Fax": null,
      "cmp_AFM": null,
      "cmp_DUNSNumber": null,
      "cmp_LastUpdateTime": null
    },
    {
      "dep_ID": 23,
      "dep_Code": "GC",
      "cmp_FullName": "cmp_FullName4981",
      "cmp_Address": null,
      "cmp_City": null,
      "cmp_ZipCode": null,
      "cmp_Phone": "Phone4981",
      "cmp_Responsible": "cmp_Responsible4981",
      "cmp_Fax": null,
      "cmp_AFM": null,
      "cmp_DUNSNumber": null,
      "cmp_LastUpdateTime": null
    },
    {
      "dep_ID": 24,
      "dep_Code": "AS",
      "cmp_FullName": "cmp_FullName4982",
      "cmp_Address": null,
      "cmp_City": null,
      "cmp_ZipCode": null,
      "cmp_Phone": "Phone4982",
      "cmp_Responsible": "cmp_Responsible4982",
      "cmp_Fax": null,
      "cmp_AFM": null,
      "cmp_DUNSNumber": null,
      "cmp_LastUpdateTime": null
    },
    {
      "dep_ID": 25,
      "dep_Code": "CONB",
      "cmp_FullName": "cmp_FullName4983",
      "cmp_Address": null,
      "cmp_City": null,
      "cmp_ZipCode": null,
      "cmp_Phone": "Phone4983",
      "cmp_Responsible": "cmp_Responsible4983",
      "cmp_Fax": null,
      "cmp_AFM": null,
      "cmp_DUNSNumber": null,
      "cmp_LastUpdateTime": null
    },
    {
      "dep_ID": 26,
      "dep_Code": "MQ",
      "cmp_FullName": "cmp_FullName4984",
      "cmp_Address": null,
      "cmp_City": null,
      "cmp_ZipCode": null,
      "cmp_Phone": "Phone4984",
      "cmp_Responsible": "cmp_Responsible4984",
      "cmp_Fax": null,
      "cmp_AFM": null,
      "cmp_DUNSNumber": null,
      "cmp_LastUpdateTime": null
    },
    {
      "dep_ID": 27,
      "dep_Code": "WAL",
      "cmp_FullName": "cmp_FullName4985",
      "cmp_Address": null,
      "cmp_City": null,
      "cmp_ZipCode": null,
      "cmp_Phone": "Phone4985",
      "cmp_Responsible": "cmp_Responsible4985",
      "cmp_Fax": null,
      "cmp_AFM": null,
      "cmp_DUNSNumber": null,
      "cmp_LastUpdateTime": null
    },
    {
      "dep_ID": 28,
      "dep_Code": "CH",
      "cmp_FullName": "cmp_FullName4986",
      "cmp_Address": "\u05E8\u05D7\u05D5\u05D1\u05EA \u05D4\u05DB\u05E0\u05E8\u05EA 12, \u05E7\u05E8\u05D9\u05EA \u05E9\u05D3\u05D4 \u05D4\u05EA\u05E2\u05D5\u05E4\u05D4 - \u05D0\u05D9\u05D9\u05E8\u05E4\u05D5\u05E8\u05D8 \u05E1\u05D9\u05D8\u05D9 ",
      "cmp_City": "\u05DC\u05D5\u05D3",
      "cmp_ZipCode": "7019802",
      "cmp_Phone": "Phone4986",
      "cmp_Responsible": "cmp_Responsible4986",
      "cmp_Fax": null,
      "cmp_AFM": null,
      "cmp_DUNSNumber": null,
      "cmp_LastUpdateTime": null
    },
    {
      "dep_ID": 29,
      "dep_Code": "URBAN",
      "cmp_FullName": "cmp_FullName4987",
      "cmp_Address": null,
      "cmp_City": "\u05D1\u05E0\u05D9 \u05D3\u05E8\u05D5\u05DD",
      "cmp_ZipCode": null,
      "cmp_Phone": "Phone4987",
      "cmp_Responsible": "cmp_Responsible4987",
      "cmp_Fax": null,
      "cmp_AFM": null,
      "cmp_DUNSNumber": null,
      "cmp_LastUpdateTime": null
    },
    {
      "dep_ID": 30,
      "dep_Code": "EG",
      "cmp_FullName": "cmp_FullName4988",
      "cmp_Address": null,
      "cmp_City": null,
      "cmp_ZipCode": null,
      "cmp_Phone": "Phone4988",
      "cmp_Responsible": "cmp_Responsible4988",
      "cmp_Fax": null,
      "cmp_AFM": null,
      "cmp_DUNSNumber": null,
      "cmp_LastUpdateTime": "2024-12-11T17:21:13.0430000"
    },
    {
      "dep_ID": 37,
      "dep_Code": "YAN",
      "cmp_FullName": "cmp_FullName4990",
      "cmp_Address": null,
      "cmp_City": null,
      "cmp_ZipCode": null,
      "cmp_Phone": "Phone4990",
      "cmp_Responsible": "cmp_Responsible4990",
      "cmp_Fax": null,
      "cmp_AFM": null,
      "cmp_DUNSNumber": null,
      "cmp_LastUpdateTime": null
    },
    {
      "dep_ID": 38,
      "dep_Code": "ANIX",
      "cmp_FullName": "cmp_FullName4991",
      "cmp_Address": null,
      "cmp_City": null,
      "cmp_ZipCode": null,
      "cmp_Phone": "Phone4991",
      "cmp_Responsible": "cmp_Responsible4991",
      "cmp_Fax": null,
      "cmp_AFM": null,
      "cmp_DUNSNumber": null,
      "cmp_LastUpdateTime": null
    },
    {
      "dep_ID": 39,
      "dep_Code": "SM",
      "cmp_FullName": "cmp_FullName4992",
      "cmp_Address": "\u05D4\u05E9\u05E8\u05D5\u05DF 5 \u05E7.\u05E9\u05D3\u05D4 \u05D4\u05EA\u05E2\u05D5\u05E4\u05D4",
      "cmp_City": null,
      "cmp_ZipCode": null,
      "cmp_Phone": "Phone4992",
      "cmp_Responsible": "cmp_Responsible4992",
      "cmp_Fax": null,
      "cmp_AFM": null,
      "cmp_DUNSNumber": null,
      "cmp_LastUpdateTime": null
    },
    {
      "dep_ID": 43,
      "dep_Code": "RNL",
      "cmp_FullName": "cmp_FullName4993",
      "cmp_Address": "\u05D4\u05DB\u05D9\u05E9\u05D5\u05E8 49",
      "cmp_City": "\u05D7\u05D5\u05DC\u05D5\u05DF",
      "cmp_ZipCode": null,
      "cmp_Phone": "Phone4993",
      "cmp_Responsible": "cmp_Responsible4993",
      "cmp_Fax": null,
      "cmp_AFM": null,
      "cmp_DUNSNumber": null,
      "cmp_LastUpdateTime": "2023-04-13T10:48:38.4030000"
    },
    {
      "dep_ID": 44,
      "dep_Code": "REDM",
      "cmp_FullName": "cmp_FullName4994",
      "cmp_Address": null,
      "cmp_City": null,
      "cmp_ZipCode": null,
      "cmp_Phone": "Phone4994",
      "cmp_Responsible": "cmp_Responsible4994",
      "cmp_Fax": null,
      "cmp_AFM": null,
      "cmp_DUNSNumber": null,
      "cmp_LastUpdateTime": null
    },
    {
      "dep_ID": 45,
      "dep_Code": "DAL",
      "cmp_FullName": "cmp_FullName4995",
      "cmp_Address": "\u05D4\u05DE\u05E6\u05E4\u05DF 2 \u05D0.\u05EA \u05E6\u05E4\u05D5\u05E0\u05D9 \u05D0\u05E9\u05D3\u05D5\u05D3",
      "cmp_City": null,
      "cmp_ZipCode": null,
      "cmp_Phone": "Phone4995",
      "cmp_Responsible": "cmp_Responsible4995",
      "cmp_Fax": null,
      "cmp_AFM": null,
      "cmp_DUNSNumber": null,
      "cmp_LastUpdateTime": null
    },
    {
      "dep_ID": 48,
      "dep_Code": "TOPT",
      "cmp_FullName": "cmp_FullName4996",
      "cmp_Address": null,
      "cmp_City": null,
      "cmp_ZipCode": null,
      "cmp_Phone": "Phone4996",
      "cmp_Responsible": "cmp_Responsible4996",
      "cmp_Fax": null,
      "cmp_AFM": null,
      "cmp_DUNSNumber": null,
      "cmp_LastUpdateTime": null
    },
    {
      "dep_ID": 49,
      "dep_Code": "SE",
      "cmp_FullName": "cmp_FullName4997",
      "cmp_Address": "\u05E7\u05D3\u05D9\u05DE\u05D4-\u05E6\u05D5\u05E8\u05DF",
      "cmp_City": "\u05E7\u05D3\u05D9\u05DE\u05D4-\u05E6\u05D5\u05E8\u05DF",
      "cmp_ZipCode": null,
      "cmp_Phone": "Phone4997",
      "cmp_Responsible": "cmp_Responsible4997",
      "cmp_Fax": null,
      "cmp_AFM": null,
      "cmp_DUNSNumber": null,
      "cmp_LastUpdateTime": null
    },
    {
      "dep_ID": 50,
      "dep_Code": "HZL",
      "cmp_FullName": "cmp_FullName4998",
      "cmp_Address": "\u05E8\u05D0\u05D5\u05DC \u05D5\u05DC\u05E0\u05D1\u05E8\u05D2 2 \u05EA\u05DC \u05D0\u05D1\u05D9\u05D1-\u05D9\u05E4\u05D5",
      "cmp_City": "\u05EA\u05DC \u05D0\u05D1\u05D9\u05D1-\u05D9\u05E4\u05D5",
      "cmp_ZipCode": null,
      "cmp_Phone": "Phone4998",
      "cmp_Responsible": "cmp_Responsible4998",
      "cmp_Fax": null,
      "cmp_AFM": null,
      "cmp_DUNSNumber": null,
      "cmp_LastUpdateTime": null
    },
    {
      "dep_ID": 51,
      "dep_Code": "AG",
      "cmp_FullName": "cmp_FullName4999",
      "cmp_Address": "\u05D4\u05D1\u05E8\u05D6\u05DC 11 \u05EA\u05DC \u05D0\u05D1\u05D9\u05D1-\u05D9\u05E4\u05D5",
      "cmp_City": "\u05EA\u05DC \u05D0\u05D1\u05D9\u05D1-\u05D9\u05E4\u05D5",
      "cmp_ZipCode": null,
      "cmp_Phone": "Phone4999",
      "cmp_Responsible": "cmp_Responsible4999",
      "cmp_Fax": null,
      "cmp_AFM": null,
      "cmp_DUNSNumber": null,
      "cmp_LastUpdateTime": "2023-05-03T17:23:02.8470000"
    },
    {
      "dep_ID": 52,
      "dep_Code": "BT",
      "cmp_FullName": "cmp_FullName5000",
      "cmp_Address": "\u05D3\u05D9\u05D6\u05D9\u05E0\u05D2\u05D5\u05E3 231",
      "cmp_City": "\u05EA\u05DC \u05D0\u05D1\u05D9\u05D1-\u05D9\u05E4\u05D5",
      "cmp_ZipCode": null,
      "cmp_Phone": "Phone5000",
      "cmp_Responsible": "cmp_Responsible5000",
      "cmp_Fax": null,
      "cmp_AFM": null,
      "cmp_DUNSNumber": null,
      "cmp_LastUpdateTime": null
    },
    {
      "dep_ID": 53,
      "dep_Code": "BSB",
      "cmp_FullName": "cmp_FullName5001",
      "cmp_Address": "\u05D0\u05DD \u05D4\u05E7\u05D1\u05D5\u05E6\u05D5\u05EA 22",
      "cmp_City": "\u05D4\u05D5\u05D3 \u05D4\u05E9\u05E8\u05D5\u05DF",
      "cmp_ZipCode": "4537563",
      "cmp_Phone": "Phone5001",
      "cmp_Responsible": "cmp_Responsible5001",
      "cmp_Fax": null,
      "cmp_AFM": null,
      "cmp_DUNSNumber": null,
      "cmp_LastUpdateTime": null
    },
    {
      "dep_ID": 55,
      "dep_Code": "UPS",
      "cmp_FullName": "cmp_FullName5003",
      "cmp_Address": "\u05E6\u05DC\u05E2 \u05D4\u05D4\u05E8 36 \u05DE\u05D5\u05D3\u05D9\u05E2\u05D9\u05DF \u05DE\u05DB\u05D1\u05D9\u05DD \u05E8\u05E2\u05D5\u05EA",
      "cmp_City": "\u05DE\u05D5\u05D3\u05D9\u05E2\u05D9\u05DF \u05DE\u05DB\u05D1\u05D9\u05DD \u05E8\u05E2\u05D5\u05EA",
      "cmp_ZipCode": null,
      "cmp_Phone": "Phone5003",
      "cmp_Responsible": "cmp_Responsible5003",
      "cmp_Fax": null,
      "cmp_AFM": null,
      "cmp_DUNSNumber": null,
      "cmp_LastUpdateTime": null
    },
    {
      "dep_ID": 56,
      "dep_Code": "UPSS",
      "cmp_FullName": "cmp_FullName5004",
      "cmp_Address": "\u05D2\u05D1\u05E2\u05EA \u05D1\u05E8\u05E0\u05E8",
      "cmp_City": "\u05D2\u05D1\u05E2\u05EA \u05D1\u05E8\u05E0\u05E8",
      "cmp_ZipCode": null,
      "cmp_Phone": "Phone5004",
      "cmp_Responsible": "cmp_Responsible5004",
      "cmp_Fax": null,
      "cmp_AFM": null,
      "cmp_DUNSNumber": null,
      "cmp_LastUpdateTime": null
    },
    {
      "dep_ID": 57,
      "dep_Code": "Joe",
      "cmp_FullName": "cmp_FullName5005",
      "cmp_Address": "\u05D7\u05D5\u05E6\u05D1\u05D9\u05DD 5",
      "cmp_City": "\u05DE\u05D1\u05E9\u05E8\u05EA \u05E6\u05D9\u05D5\u05DF",
      "cmp_ZipCode": null,
      "cmp_Phone": "Phone5005",
      "cmp_Responsible": "cmp_Responsible5005",
      "cmp_Fax": null,
      "cmp_AFM": null,
      "cmp_DUNSNumber": null,
      "cmp_LastUpdateTime": "2022-11-07T17:29:53.4670000"
    },
    {
      "dep_ID": 58,
      "dep_Code": "ZIF",
      "cmp_FullName": "cmp_FullName5006",
      "cmp_Address": "\u05D4\u05D7\u05D5\u05DE\u05D4 4",
      "cmp_City": "\u05E8\u05D0\u05E9\u05D5\u05DF \u05DC\u05E6\u05D9\u05D5\u05DF",
      "cmp_ZipCode": "7565504",
      "cmp_Phone": "Phone5006",
      "cmp_Responsible": "cmp_Responsible5006",
      "cmp_Fax": null,
      "cmp_AFM": null,
      "cmp_DUNSNumber": null,
      "cmp_LastUpdateTime": "2022-11-15T13:01:38.0770000"
    },
    {
      "dep_ID": 59,
      "dep_Code": "ADV",
      "cmp_FullName": "cmp_FullName5007",
      "cmp_Address": "\u05E2\u05EA\u05D9\u05E8 \u05D9\u05D3\u05E2 16",
      "cmp_City": "\u05DB\u05E4\u05E8 \u05E1\u05D1\u05D0",
      "cmp_ZipCode": "4464321",
      "cmp_Phone": "Phone5007",
      "cmp_Responsible": "cmp_Responsible5007",
      "cmp_Fax": null,
      "cmp_AFM": null,
      "cmp_DUNSNumber": null,
      "cmp_LastUpdateTime": "2022-11-15T14:43:36.4270000"
    },
    {
      "dep_ID": 60,
      "dep_Code": "CMS",
      "cmp_FullName": "cmp_FullName5008",
      "cmp_Address": "\u05E6\u05DC\u05E2 \u05D4\u05D4\u05E8 36",
      "cmp_City": "\u05DE\u05D5\u05D3\u05D9\u05E2\u05D9\u05DF \u05DE\u05DB\u05D1\u05D9\u05DD \u05E8\u05E2\u05D5\u05EA",
      "cmp_ZipCode": null,
      "cmp_Phone": "Phone5008",
      "cmp_Responsible": "cmp_Responsible5008",
      "cmp_Fax": null,
      "cmp_AFM": null,
      "cmp_DUNSNumber": null,
      "cmp_LastUpdateTime": "2022-11-21T10:16:04.7070000"
    },
    {
      "dep_ID": 61,
      "dep_Code": "VDG",
      "cmp_FullName": "cmp_FullName5009",
      "cmp_Address": "\u05E6\u05DC\u05E2 \u05D4\u05D4\u05E8 36",
      "cmp_City": "\u05DE\u05D5\u05D3\u05D9\u05E2\u05D9\u05DF \u05DE\u05DB\u05D1\u05D9\u05DD \u05E8\u05E2\u05D5\u05EA",
      "cmp_ZipCode": null,
      "cmp_Phone": "Phone5009",
      "cmp_Responsible": "cmp_Responsible5009",
      "cmp_Fax": null,
      "cmp_AFM": null,
      "cmp_DUNSNumber": null,
      "cmp_LastUpdateTime": "2022-11-21T10:17:43.8330000"
    },
    {
      "dep_ID": 62,
      "dep_Code": "TR",
      "cmp_FullName": "cmp_FullName5010",
      "cmp_Address": "\u05E6\u05DC\u05E2 \u05D4\u05D4\u05E8 36",
      "cmp_City": "\u05DE\u05D5\u05D3\u05D9\u05E2\u05D9\u05DF \u05DE\u05DB\u05D1\u05D9\u05DD \u05E8\u05E2\u05D5\u05EA",
      "cmp_ZipCode": null,
      "cmp_Phone": "Phone5010",
      "cmp_Responsible": "cmp_Responsible5010",
      "cmp_Fax": null,
      "cmp_AFM": null,
      "cmp_DUNSNumber": null,
      "cmp_LastUpdateTime": "2022-11-21T10:19:38.3030000"
    },
    {
      "dep_ID": 63,
      "dep_Code": "WE",
      "cmp_FullName": "cmp_FullName5011",
      "cmp_Address": "\u05D4\u05E9\u05D7\u05DD 30",
      "cmp_City": "\u05E4\u05EA\u05D7 \u05EA\u05E7\u05D5\u05D5\u05D4",
      "cmp_ZipCode": null,
      "cmp_Phone": "Phone5011",
      "cmp_Responsible": "cmp_Responsible5011",
      "cmp_Fax": null,
      "cmp_AFM": null,
      "cmp_DUNSNumber": null,
      "cmp_LastUpdateTime": "2022-11-27T17:15:04.3100000"
    },
    {
      "dep_ID": 64,
      "dep_Code": "CMS2",
      "cmp_FullName": "cmp_FullName5012",
      "cmp_Address": "\u05E6\u05DC\u05E2 \u05D4\u05D4\u05E8 36",
      "cmp_City": "\u05DE\u05D5\u05D3\u05D9\u05E2\u05D9\u05DF \u05DE\u05DB\u05D1\u05D9\u05DD \u05E8\u05E2\u05D5\u05EA",
      "cmp_ZipCode": null,
      "cmp_Phone": "Phone5012",
      "cmp_Responsible": "cmp_Responsible5012",
      "cmp_Fax": null,
      "cmp_AFM": null,
      "cmp_DUNSNumber": null,
      "cmp_LastUpdateTime": "2022-11-30T12:20:51.3900000"
    },
    {
      "dep_ID": 65,
      "dep_Code": "HHL",
      "cmp_FullName": "cmp_FullName5013",
      "cmp_Address": "\u05D9\u05D5\u05E0\u05EA\u05DF \u05D1\u05DF \u05E2\u05D5\u05D6\u05D9\u05D0\u05DC 61",
      "cmp_City": "\u05D0\u05DC\u05E2\u05D3",
      "cmp_ZipCode": null,
      "cmp_Phone": "Phone5013",
      "cmp_Responsible": "cmp_Responsible5013",
      "cmp_Fax": null,
      "cmp_AFM": null,
      "cmp_DUNSNumber": "066704891",
      "cmp_LastUpdateTime": "2022-12-01T17:59:41.4730000"
    },
    {
      "dep_ID": 66,
      "dep_Code": "CLD",
      "cmp_FullName": "cmp_FullName5014",
      "cmp_Address": null,
      "cmp_City": null,
      "cmp_ZipCode": null,
      "cmp_Phone": "Phone5014",
      "cmp_Responsible": "cmp_Responsible5014",
      "cmp_Fax": null,
      "cmp_AFM": null,
      "cmp_DUNSNumber": null,
      "cmp_LastUpdateTime": "2022-12-26T17:15:25.9630000"
    },
    {
      "dep_ID": 67,
      "dep_Code": "TOMJ",
      "cmp_FullName": "cmp_FullName5015",
      "cmp_Address": "\u05D4\u05D9\u05E8\u05E7\u05D5\u05DF 90",
      "cmp_City": "\u05EA\u05DC \u05D0\u05D1\u05D9\u05D1-\u05D9\u05E4\u05D5",
      "cmp_ZipCode": null,
      "cmp_Phone": "Phone5015",
      "cmp_Responsible": "cmp_Responsible5015",
      "cmp_Fax": null,
      "cmp_AFM": null,
      "cmp_DUNSNumber": null,
      "cmp_LastUpdateTime": "2023-01-01T18:43:05.6670000"
    },
    {
      "dep_ID": 68,
      "dep_Code": "MULV",
      "cmp_FullName": "cmp_FullName5016",
      "cmp_Address": "\u05D4\u05D0\u05E9\u05DC 5 \u05DE\u05D5\u05DC\u05D8\u05D9\u05D5\u05D5\u05D0\u05E7",
      "cmp_City": "\u05E7\u05D9\u05E1\u05E8\u05D9\u05D4",
      "cmp_ZipCode": null,
      "cmp_Phone": "Phone5016",
      "cmp_Responsible": "cmp_Responsible5016",
      "cmp_Fax": null,
      "cmp_AFM": null,
      "cmp_DUNSNumber": null,
      "cmp_LastUpdateTime": "2023-09-18T10:04:45.6230000"
    },
    {
      "dep_ID": 69,
      "dep_Code": "ZG",
      "cmp_FullName": "cmp_FullName5017",
      "cmp_Address": "\u05D3\u05E8\u05DA \u05D1\u05DF \u05E6\u05D1\u05D9 84",
      "cmp_City": "\u05EA\u05DC \u05D0\u05D1\u05D9\u05D1-\u05D9\u05E4\u05D5",
      "cmp_ZipCode": null,
      "cmp_Phone": "Phone5017",
      "cmp_Responsible": "cmp_Responsible5017",
      "cmp_Fax": null,
      "cmp_AFM": null,
      "cmp_DUNSNumber": null,
      "cmp_LastUpdateTime": "2023-02-20T15:41:05.6330000"
    },
    {
      "dep_ID": 70,
      "dep_Code": "HR",
      "cmp_FullName": "cmp_FullName5018",
      "cmp_Address": "\u05D1\u05E6\u05E8\u05D4",
      "cmp_City": "\u05D1\u05E6\u05E8\u05D4",
      "cmp_ZipCode": null,
      "cmp_Phone": "Phone5018",
      "cmp_Responsible": "cmp_Responsible5018",
      "cmp_Fax": null,
      "cmp_AFM": null,
      "cmp_DUNSNumber": null,
      "cmp_LastUpdateTime": "2023-02-27T14:24:45.1200000"
    },
    {
      "dep_ID": 72,
      "dep_Code": "IRP",
      "cmp_FullName": "cmp_FullName5019",
      "cmp_Address": "\u05D2\u05D5\u05DC\u05D3\u05D4 \u05DE\u05D0\u05D9\u05E8 5",
      "cmp_City": "\u05E0\u05E1 \u05E6\u05D9\u05D5\u05E0\u05D4",
      "cmp_ZipCode": "7403649",
      "cmp_Phone": "Phone5019",
      "cmp_Responsible": "cmp_Responsible5019",
      "cmp_Fax": null,
      "cmp_AFM": null,
      "cmp_DUNSNumber": null,
      "cmp_LastUpdateTime": "2023-03-01T16:13:59.5270000"
    },
    {
      "dep_ID": 73,
      "dep_Code": "SAM",
      "cmp_FullName": "cmp_FullName5020",
      "cmp_Address": "\u05D4\u05DE\u05E4\u05DC\u05E1\u05D9\u05DD 9 , \u05E4\u05EA\u05D7 \u05EA\u05E7\u05D5\u05D5\u05D4",
      "cmp_City": "\u05E4\u05EA\u05D7 \u05EA\u05E7\u05D5\u05D5\u05D4",
      "cmp_ZipCode": null,
      "cmp_Phone": "Phone5020",
      "cmp_Responsible": "cmp_Responsible5020",
      "cmp_Fax": null,
      "cmp_AFM": null,
      "cmp_DUNSNumber": null,
      "cmp_LastUpdateTime": "2023-05-03T17:31:06.6630000"
    },
    {
      "dep_ID": 74,
      "dep_Code": "QW",
      "cmp_FullName": "cmp_FullName5021",
      "cmp_Address": "\u05D1\u05D9\u05EA \u05E0\u05D7\u05DE\u05D9\u05D4",
      "cmp_City": "\u05D1\u05D9\u05EA \u05E0\u05D7\u05DE\u05D9\u05D4",
      "cmp_ZipCode": null,
      "cmp_Phone": "Phone5021",
      "cmp_Responsible": "cmp_Responsible5021",
      "cmp_Fax": null,
      "cmp_AFM": null,
      "cmp_DUNSNumber": "514882745",
      "cmp_LastUpdateTime": "2023-05-02T16:05:46.2800000"
    },
    {
      "dep_ID": 75,
      "dep_Code": "BYN",
      "cmp_FullName": "cmp_FullName5022",
      "cmp_Address": "\u05E8\u05D0\u05D5\u05DC \u05D5\u05DC\u05E0\u05D1\u05E8\u05D2 24, \u05EA\u05DC \u05D0\u05D1\u05D9\u05D1 \u05D9\u05E4\u05D5",
      "cmp_City": "\u05EA\u05DC \u05D0\u05D1\u05D9\u05D1 \u05D9\u05E4\u05D5",
      "cmp_ZipCode": null,
      "cmp_Phone": "Phone5022",
      "cmp_Responsible": "cmp_Responsible5022",
      "cmp_Fax": null,
      "cmp_AFM": null,
      "cmp_DUNSNumber": null,
      "cmp_LastUpdateTime": "2023-06-07T13:56:03.8130000"
    },
    {
      "dep_ID": 76,
      "dep_Code": "SMB",
      "cmp_FullName": "cmp_FullName5023",
      "cmp_Address": "\u05D2\u05D5\u05DC\u05DF 1, \u05E7\u05E8\u05D9\u05EA \u05E9\u05D3\u05D4 \u05EA\u05E2\u05D5\u05E4\u05D4",
      "cmp_City": "\u05E7\u05E8\u05D9\u05EA \u05E9\u05D3\u05D4 \u05EA\u05E2\u05D5\u05E4\u05D4",
      "cmp_ZipCode": null,
      "cmp_Phone": "Phone5023",
      "cmp_Responsible": "cmp_Responsible5023",
      "cmp_Fax": null,
      "cmp_AFM": null,
      "cmp_DUNSNumber": "512518143",
      "cmp_LastUpdateTime": "2023-06-12T16:47:00.9930000"
    },
    {
      "dep_ID": 77,
      "dep_Code": "DBIO",
      "cmp_FullName": "cmp_FullName5024",
      "cmp_Address": "\u05D4\u05DE\u05D3\u05E2 8 \u05E8\u05D7\u05D5\u05D1\u05D5\u05EA",
      "cmp_City": "\u05E8\u05D7\u05D5\u05D1\u05D5\u05EA",
      "cmp_ZipCode": "7670308",
      "cmp_Phone": "Phone5024",
      "cmp_Responsible": "cmp_Responsible5024",
      "cmp_Fax": null,
      "cmp_AFM": "512664814",
      "cmp_DUNSNumber": null,
      "cmp_LastUpdateTime": "2023-07-05T16:52:04.8430000"
    },
    {
      "dep_ID": 78,
      "dep_Code": "YDL",
      "cmp_FullName": "cmp_FullName5025",
      "cmp_Address": null,
      "cmp_City": null,
      "cmp_ZipCode": null,
      "cmp_Phone": "Phone5025",
      "cmp_Responsible": "cmp_Responsible5025",
      "cmp_Fax": null,
      "cmp_AFM": null,
      "cmp_DUNSNumber": null,
      "cmp_LastUpdateTime": "2023-07-09T10:37:54.4570000"
    },
    {
      "dep_ID": 79,
      "dep_Code": "ISI",
      "cmp_FullName": "cmp_FullName5026",
      "cmp_Address": "\u05E9\u05D7\u05DD 32 \u05D1\u05D9\u05EA \u05D0\u05DE\u05E8\u05D2\u05D3\r\n\u05E7\u05E8\u05D9\u05EA \u05DE\u05D8\u05DC\u05D5\u05DF",
      "cmp_City": "\u05E4\u05EA\u05D7 \u05EA\u05E7\u05D5\u05D5\u05D4",
      "cmp_ZipCode": "4951727",
      "cmp_Phone": "Phone5026",
      "cmp_Responsible": "cmp_Responsible5026",
      "cmp_Fax": "03-9229750",
      "cmp_AFM": null,
      "cmp_DUNSNumber": "520030784",
      "cmp_LastUpdateTime": "2023-09-10T15:19:25.9230000"
    },
    {
      "dep_ID": 80,
      "dep_Code": "UTR",
      "cmp_FullName": "cmp_FullName5027",
      "cmp_Address": "\u05E9\u05E8\u05D5\u05DF 5, \u05E7\u05E8\u05D9\u05EA \u05E9\u05D3\u05D4 \u05EA\u05E2\u05D5\u05E4\u05D4",
      "cmp_City": "\u05DC\u05D5\u05D3",
      "cmp_ZipCode": null,
      "cmp_Phone": "Phone5027",
      "cmp_Responsible": "cmp_Responsible5027",
      "cmp_Fax": null,
      "cmp_AFM": null,
      "cmp_DUNSNumber": null,
      "cmp_LastUpdateTime": "2023-08-07T17:32:00.3270000"
    },
    {
      "dep_ID": 81,
      "dep_Code": "ATWI",
      "cmp_FullName": "cmp_FullName5028",
      "cmp_Address": "\u05E9\u05D1\u05D9\u05D8 1, \u05E8\u05D0\u05E9\u05D5\u05DF \u05DC\u05E6\u05D9\u05D5\u05DF",
      "cmp_City": "\u05E8\u05D0\u05E9\u05D5\u05DF \u05DC\u05E6\u05D9\u05D5\u05DF",
      "cmp_ZipCode": "7559914",
      "cmp_Phone": "Phone5028",
      "cmp_Responsible": "cmp_Responsible5028",
      "cmp_Fax": null,
      "cmp_AFM": null,
      "cmp_DUNSNumber": "516767340",
      "cmp_LastUpdateTime": "2023-08-07T18:07:38.3830000"
    },
    {
      "dep_ID": 82,
      "dep_Code": "PBT",
      "cmp_FullName": "cmp_FullName5029",
      "cmp_Address": "\u05D1\u05E8\u05DC\u05D9\u05E0\u05E8 4, \u05EA\u05DC \u05D0\u05D1\u05D9\u05D1-\u05D9\u05E4\u05D5",
      "cmp_City": "\u05EA\u05DC \u05D0\u05D1\u05D9\u05D1-\u05D9\u05E4\u05D5",
      "cmp_ZipCode": "6905704",
      "cmp_Phone": "Phone5029",
      "cmp_Responsible": "cmp_Responsible5029",
      "cmp_Fax": null,
      "cmp_AFM": null,
      "cmp_DUNSNumber": null,
      "cmp_LastUpdateTime": "2024-04-10T12:53:01.7000000"
    },
    {
      "dep_ID": 83,
      "dep_Code": "TOUCH",
      "cmp_FullName": "cmp_FullName5030",
      "cmp_Address": "\u05E8\u05D7\u05D5\u05D1 \u05D4\u05DE\u05E2\u05D9\u05D9\u05DF 2",
      "cmp_City": "\u05DE\u05D5\u05D3\u05D9\u05E2\u05D9\u05DF-\u05DE\u05DB\u05D1\u05D9\u05DD-\u05E8\u05E2\u05D5\u05EA",
      "cmp_ZipCode": null,
      "cmp_Phone": "Phone5030",
      "cmp_Responsible": "cmp_Responsible5030",
      "cmp_Fax": null,
      "cmp_AFM": null,
      "cmp_DUNSNumber": null,
      "cmp_LastUpdateTime": "2023-10-09T13:00:00.0500000"
    },
    {
      "dep_ID": 84,
      "dep_Code": "COL",
      "cmp_FullName": "cmp_FullName5031",
      "cmp_Address": "\u05D4\u05E9\u05E8\u05D5\u05DF 3, \u05E7\u05E8\u05D9\u05D9\u05EA \u05E9\u05D3\u05D4 \u05D4\u05EA\u05E2\u05D5\u05E4\u05D4 ",
      "cmp_City": "\u05DC\u05D5\u05D3",
      "cmp_ZipCode": null,
      "cmp_Phone": "Phone5031",
      "cmp_Responsible": "cmp_Responsible5031",
      "cmp_Fax": null,
      "cmp_AFM": null,
      "cmp_DUNSNumber": null,
      "cmp_LastUpdateTime": "2023-10-12T11:49:37.0730000"
    },
    {
      "dep_ID": 85,
      "dep_Code": "MAB",
      "cmp_FullName": "cmp_FullName5032",
      "cmp_Address": "\u05E0\u05D5\u05D5\u05D4 \u05DE\u05D1\u05D8\u05D7",
      "cmp_City": "\u05E0\u05D5\u05D5\u05D4 \u05DE\u05D1\u05D8\u05D7",
      "cmp_ZipCode": null,
      "cmp_Phone": "Phone5032",
      "cmp_Responsible": "cmp_Responsible5032",
      "cmp_Fax": null,
      "cmp_AFM": null,
      "cmp_DUNSNumber": null,
      "cmp_LastUpdateTime": "2024-06-25T10:12:33.1470000"
    },
    {
      "dep_ID": 91,
      "dep_Code": "TAG",
      "cmp_FullName": "cmp_FullName5034",
      "cmp_Address": null,
      "cmp_City": null,
      "cmp_ZipCode": null,
      "cmp_Phone": "Phone5034",
      "cmp_Responsible": "cmp_Responsible5034",
      "cmp_Fax": null,
      "cmp_AFM": null,
      "cmp_DUNSNumber": null,
      "cmp_LastUpdateTime": "2023-12-27T11:49:02.5500000"
    },
    {
      "dep_ID": 92,
      "dep_Code": "POLK",
      "cmp_FullName": "cmp_FullName5035",
      "cmp_Address": "\u05D4\u05DE\u05E4\u05DC\u05E1\u05D9\u05DD 9 , \u05E4\u05EA\u05D7 \u05EA\u05E7\u05D5\u05D5\u05D4",
      "cmp_City": "\u05E4\u05EA\u05D7 \u05EA\u05E7\u05D5\u05D5\u05D4",
      "cmp_ZipCode": null,
      "cmp_Phone": "Phone5035",
      "cmp_Responsible": "cmp_Responsible5035",
      "cmp_Fax": null,
      "cmp_AFM": null,
      "cmp_DUNSNumber": null,
      "cmp_LastUpdateTime": "2023-11-30T13:10:45.9730000"
    },
    {
      "dep_ID": 93,
      "dep_Code": "PRC",
      "cmp_FullName": "cmp_FullName5036",
      "cmp_Address": null,
      "cmp_City": null,
      "cmp_ZipCode": null,
      "cmp_Phone": "Phone5036",
      "cmp_Responsible": "cmp_Responsible5036",
      "cmp_Fax": null,
      "cmp_AFM": null,
      "cmp_DUNSNumber": null,
      "cmp_LastUpdateTime": "2023-12-03T11:07:27.2100000"
    },
    {
      "dep_ID": 94,
      "dep_Code": "DBM",
      "cmp_FullName": "cmp_FullName5037",
      "cmp_Address": null,
      "cmp_City": null,
      "cmp_ZipCode": null,
      "cmp_Phone": "Phone5037",
      "cmp_Responsible": "cmp_Responsible5037",
      "cmp_Fax": null,
      "cmp_AFM": null,
      "cmp_DUNSNumber": null,
      "cmp_LastUpdateTime": "2023-12-03T13:08:18.3600000"
    },
    {
      "dep_ID": 95,
      "dep_Code": "AGM",
      "cmp_FullName": "cmp_FullName5038",
      "cmp_Address": "\u05D6\u0027\u05D1\u05D5\u05D8\u05D9\u05E0\u05E1\u05E7\u05D9 147",
      "cmp_City": "\u05E8\u05DE\u05EA \u05D2\u05DF",
      "cmp_ZipCode": null,
      "cmp_Phone": "Phone5038",
      "cmp_Responsible": "cmp_Responsible5038",
      "cmp_Fax": null,
      "cmp_AFM": null,
      "cmp_DUNSNumber": null,
      "cmp_LastUpdateTime": "2024-03-20T12:58:06.2330000"
    },
    {
      "dep_ID": 96,
      "dep_Code": "TIP",
      "cmp_FullName": "cmp_FullName5039",
      "cmp_Address": null,
      "cmp_City": null,
      "cmp_ZipCode": null,
      "cmp_Phone": "Phone5039",
      "cmp_Responsible": "cmp_Responsible5039",
      "cmp_Fax": null,
      "cmp_AFM": null,
      "cmp_DUNSNumber": null,
      "cmp_LastUpdateTime": "2023-12-05T11:55:02.3070000"
    },
    {
      "dep_ID": 97,
      "dep_Code": "YGA",
      "cmp_FullName": "cmp_FullName5040",
      "cmp_Address": "\u05D7\u05D9\u05D9\u05DD \u05DC\u05D1\u05E0\u05D5\u05DF 21 \u05EA\u05DC \u05D0\u05D1\u05D9\u05D1",
      "cmp_City": "\u05EA\u05DC \u05D0\u05D1\u05D9\u05D1",
      "cmp_ZipCode": null,
      "cmp_Phone": "Phone5040",
      "cmp_Responsible": "cmp_Responsible5040",
      "cmp_Fax": null,
      "cmp_AFM": null,
      "cmp_DUNSNumber": null,
      "cmp_LastUpdateTime": "2025-03-02T12:21:29.6630000"
    },
    {
      "dep_ID": 98,
      "dep_Code": "DFH",
      "cmp_FullName": "cmp_FullName5041",
      "cmp_Address": "\u05D0\u05DC\u05D9\u05D4\u05D5 \u05D0\u05D9\u05EA\u05DF 13 \u05E8\u05D0\u05E9\u05D5\u05DF \u05DC\u05E6\u05D9\u05D5\u05DF",
      "cmp_City": "\u05E8\u05D0\u05E9\u05D5\u05DF \u05DC\u05E6\u05D9\u05D5\u05DF",
      "cmp_ZipCode": null,
      "cmp_Phone": "Phone5041",
      "cmp_Responsible": "cmp_Responsible5041",
      "cmp_Fax": null,
      "cmp_AFM": null,
      "cmp_DUNSNumber": null,
      "cmp_LastUpdateTime": "2023-12-17T14:13:06.0970000"
    },
    {
      "dep_ID": 99,
      "dep_Code": "AGAM",
      "cmp_FullName": "cmp_FullName5043",
      "cmp_Address": null,
      "cmp_City": null,
      "cmp_ZipCode": null,
      "cmp_Phone": "Phone5043",
      "cmp_Responsible": "cmp_Responsible5043",
      "cmp_Fax": null,
      "cmp_AFM": null,
      "cmp_DUNSNumber": null,
      "cmp_LastUpdateTime": "2023-12-24T14:47:26.1770000"
    },
    {
      "dep_ID": 100,
      "dep_Code": "MH",
      "cmp_FullName": "cmp_FullName5044",
      "cmp_Address": "\u05DE\u05DC\u05DB\u05D9 \u05E6\u05D3\u05E7 12",
      "cmp_City": "\u05E8\u05DE\u05EA \u05D2\u05DF",
      "cmp_ZipCode": null,
      "cmp_Phone": "Phone5044",
      "cmp_Responsible": "cmp_Responsible5044",
      "cmp_Fax": null,
      "cmp_AFM": null,
      "cmp_DUNSNumber": "516880150",
      "cmp_LastUpdateTime": "2024-01-07T16:06:25.9070000"
    },
    {
      "dep_ID": 101,
      "dep_Code": "SN",
      "cmp_FullName": "cmp_FullName5045",
      "cmp_Address": "\u05E0\u05D7\u05DC \u05D2\u05DC\u05D9\u05DD 19",
      "cmp_City": "\u05DB\u05E4\u05E8 \u05D9\u05D5\u05E0\u05D4",
      "cmp_ZipCode": null,
      "cmp_Phone": "Phone5045",
      "cmp_Responsible": "cmp_Responsible5045",
      "cmp_Fax": null,
      "cmp_AFM": null,
      "cmp_DUNSNumber": null,
      "cmp_LastUpdateTime": "2024-01-10T14:43:37.4430000"
    },
    {
      "dep_ID": 103,
      "dep_Code": "WLA",
      "cmp_FullName": "cmp_FullName5047",
      "cmp_Address": null,
      "cmp_City": null,
      "cmp_ZipCode": null,
      "cmp_Phone": "Phone5047",
      "cmp_Responsible": "cmp_Responsible5047",
      "cmp_Fax": null,
      "cmp_AFM": null,
      "cmp_DUNSNumber": null,
      "cmp_LastUpdateTime": "2024-01-14T14:25:32.6470000"
    },
    {
      "dep_ID": 105,
      "dep_Code": "PRP",
      "cmp_FullName": "cmp_FullName5048",
      "cmp_Address": "\u05D4\u05DE\u05DC\u05D0\u05DB\u05D4 29 ",
      "cmp_City": "\u05E0\u05EA\u05E0\u05D9\u05D4",
      "cmp_ZipCode": null,
      "cmp_Phone": "Phone5048",
      "cmp_Responsible": "cmp_Responsible5048",
      "cmp_Fax": null,
      "cmp_AFM": null,
      "cmp_DUNSNumber": null,
      "cmp_LastUpdateTime": "2024-01-24T17:15:36.6870000"
    },
    {
      "dep_ID": 106,
      "dep_Code": "ETC",
      "cmp_FullName": "cmp_FullName5049",
      "cmp_Address": "\u05D0\u05E9\u05DC\u05D2\u05DF 10",
      "cmp_City": "\u05E7\u05E8\u05D9\u05EA \u05D2\u05EA",
      "cmp_ZipCode": null,
      "cmp_Phone": "Phone5049",
      "cmp_Responsible": "cmp_Responsible5049",
      "cmp_Fax": null,
      "cmp_AFM": null,
      "cmp_DUNSNumber": null,
      "cmp_LastUpdateTime": "2024-01-25T13:09:06.0570000"
    },
    {
      "dep_ID": 107,
      "dep_Code": "PRON",
      "cmp_FullName": "cmp_FullName5050",
      "cmp_Address": "\u05D4\u05D7\u05E8\u05DE\u05D5\u05DF 6",
      "cmp_City": "\u05E7\u05E8\u05D9\u05EA \u05E9\u05D3\u05D4 \u05EA\u05E2\u05D5\u05E4\u05D4",
      "cmp_ZipCode": null,
      "cmp_Phone": "Phone5050",
      "cmp_Responsible": "cmp_Responsible5050",
      "cmp_Fax": null,
      "cmp_AFM": null,
      "cmp_DUNSNumber": null,
      "cmp_LastUpdateTime": "2024-02-21T12:19:40.8270000"
    },
    {
      "dep_ID": 108,
      "dep_Code": "MYP",
      "cmp_FullName": "cmp_FullName5051",
      "cmp_Address": "\u05D0\u05D7\u05D3 \u05D4\u05E2\u05DD 72",
      "cmp_City": "\u05EA\u05DC \u05D0\u05D1\u05D9\u05D1",
      "cmp_ZipCode": null,
      "cmp_Phone": "Phone5051",
      "cmp_Responsible": "cmp_Responsible5051",
      "cmp_Fax": null,
      "cmp_AFM": null,
      "cmp_DUNSNumber": null,
      "cmp_LastUpdateTime": "2024-02-28T15:25:39.7400000"
    },
    {
      "dep_ID": 109,
      "dep_Code": "PHP",
      "cmp_FullName": "cmp_FullName5052",
      "cmp_Address": "\u05D4\u05D7\u05E8\u05D8 12 \u05D1\u05E0\u05D9\u05DF B ",
      "cmp_City": "\u05DE\u05D5\u05D3\u05D9\u05E2\u05D9\u05DF",
      "cmp_ZipCode": null,
      "cmp_Phone": "Phone5052",
      "cmp_Responsible": "cmp_Responsible5052",
      "cmp_Fax": null,
      "cmp_AFM": null,
      "cmp_DUNSNumber": null,
      "cmp_LastUpdateTime": "2024-02-28T16:24:41.2300000"
    },
    {
      "dep_ID": 110,
      "dep_Code": "BIN",
      "cmp_FullName": "cmp_FullName5053",
      "cmp_Address": "\u05E8\u05D0\u05D5\u05DC \u05D5\u05D5\u05DC\u05E0\u05D1\u05E8\u05D2 24 ",
      "cmp_City": "\u05EA\u05DC-\u05D0\u05D1\u05D9\u05D1",
      "cmp_ZipCode": null,
      "cmp_Phone": "Phone5053",
      "cmp_Responsible": "cmp_Responsible5053",
      "cmp_Fax": null,
      "cmp_AFM": null,
      "cmp_DUNSNumber": null,
      "cmp_LastUpdateTime": "2024-10-06T10:31:58.9400000"
    },
    {
      "dep_ID": 111,
      "dep_Code": "GRW",
      "cmp_FullName": "cmp_FullName5054",
      "cmp_Address": "\u05D4\u05E4\u05DC\u05DE\u05D7 53",
      "cmp_City": "\u05DE\u05D1\u05E9\u05E8\u05EA \u05E6\u05D9\u05D5\u05DF",
      "cmp_ZipCode": null,
      "cmp_Phone": "Phone5054",
      "cmp_Responsible": "cmp_Responsible5054",
      "cmp_Fax": null,
      "cmp_AFM": null,
      "cmp_DUNSNumber": null,
      "cmp_LastUpdateTime": "2024-03-11T13:48:08.1870000"
    },
    {
      "dep_ID": 112,
      "dep_Code": "B\u0026N",
      "cmp_FullName": "cmp_FullName5055",
      "cmp_Address": "\u05D3\u05E8\u05DA \u05DE\u05E0\u05D7\u05DD \u05D1\u05D2\u05D9\u05DF 75",
      "cmp_City": "\u05E4\u05EA\u05D7 \u05EA\u05E7\u05D5\u05D4",
      "cmp_ZipCode": null,
      "cmp_Phone": "Phone5055",
      "cmp_Responsible": "cmp_Responsible5055",
      "cmp_Fax": null,
      "cmp_AFM": null,
      "cmp_DUNSNumber": null,
      "cmp_LastUpdateTime": "2024-03-13T17:58:52.5270000"
    },
    {
      "dep_ID": 113,
      "dep_Code": "SDS",
      "cmp_FullName": "cmp_FullName5056",
      "cmp_Address": "\u05D4\u05D5\u05E8\u05D5\u05D1\u05D9\u05E5 5",
      "cmp_City": "\u05E8\u05D0\u05E9\u05D5\u05DF \u05DC\u05E6\u05D9\u05D5\u05DF",
      "cmp_ZipCode": null,
      "cmp_Phone": "Phone5056",
      "cmp_Responsible": "cmp_Responsible5056",
      "cmp_Fax": null,
      "cmp_AFM": null,
      "cmp_DUNSNumber": null,
      "cmp_LastUpdateTime": "2024-03-13T17:51:59.5470000"
    },
    {
      "dep_ID": 114,
      "dep_Code": "REW",
      "cmp_FullName": "cmp_FullName5057",
      "cmp_Address": null,
      "cmp_City": null,
      "cmp_ZipCode": null,
      "cmp_Phone": "Phone5057",
      "cmp_Responsible": "cmp_Responsible5057",
      "cmp_Fax": null,
      "cmp_AFM": null,
      "cmp_DUNSNumber": null,
      "cmp_LastUpdateTime": "2024-03-19T10:55:01.0430000"
    },
    {
      "dep_ID": 115,
      "dep_Code": "CTC",
      "cmp_FullName": "cmp_FullName5058",
      "cmp_Address": "\u05D7\u05D9\u05D3\u05E7\u05DC 9 \u05D1\u05E0\u05D9\u05D9\u05DF 14",
      "cmp_City": "\u05D9\u05D1\u05E0\u05D4",
      "cmp_ZipCode": null,
      "cmp_Phone": "Phone5058",
      "cmp_Responsible": "cmp_Responsible5058",
      "cmp_Fax": null,
      "cmp_AFM": null,
      "cmp_DUNSNumber": null,
      "cmp_LastUpdateTime": "2024-03-27T12:16:21.3300000"
    },
    {
      "dep_ID": 116,
      "dep_Code": "KOI",
      "cmp_FullName": "cmp_FullName5059",
      "cmp_Address": "\u05D2\u05DC\u05D2\u05DC\u05D9 \u05D4\u05E4\u05DC\u05D3\u05D4 11, \u05D1\u05E0\u05D9\u05D9\u05DF 3 \u05E7\u05D5\u05DE\u05D4 1, ",
      "cmp_City": "\u05D4\u05E8\u05E6\u05DC\u05D9\u05D4 \u05E4\u05D9\u05EA\u05D5\u05D7 ",
      "cmp_ZipCode": null,
      "cmp_Phone": "Phone5059",
      "cmp_Responsible": "cmp_Responsible5059",
      "cmp_Fax": null,
      "cmp_AFM": null,
      "cmp_DUNSNumber": null,
      "cmp_LastUpdateTime": "2024-04-04T15:11:19.1600000"
    },
    {
      "dep_ID": 117,
      "dep_Code": "LAB",
      "cmp_FullName": "cmp_FullName5060",
      "cmp_Address": null,
      "cmp_City": null,
      "cmp_ZipCode": null,
      "cmp_Phone": "Phone5060",
      "cmp_Responsible": "cmp_Responsible5060",
      "cmp_Fax": null,
      "cmp_AFM": null,
      "cmp_DUNSNumber": null,
      "cmp_LastUpdateTime": "2024-04-08T13:58:27.8600000"
    },
    {
      "dep_ID": 118,
      "dep_Code": "BYL",
      "cmp_FullName": "cmp_FullName5061",
      "cmp_Address": "\u05D0\u05D9\u05E8\u05D5\u05E1\u05D9\u05DD 9",
      "cmp_City": "\u05DB\u05E4\u05E8 \u05E1\u05D9\u05E8\u05E7\u05D9\u05DF",
      "cmp_ZipCode": null,
      "cmp_Phone": "Phone5061",
      "cmp_Responsible": "cmp_Responsible5061",
      "cmp_Fax": null,
      "cmp_AFM": null,
      "cmp_DUNSNumber": null,
      "cmp_LastUpdateTime": "2024-04-14T16:12:27.2630000"
    },
    {
      "dep_ID": 121,
      "dep_Code": "CMC",
      "cmp_FullName": "cmp_FullName5062",
      "cmp_Address": "\u05DE\u05D5\u05D8\u05D4 \u05D2\u05D5\u05E8 9",
      "cmp_City": "\u05E4\u05EA\u05D7 \u05EA\u05E7\u05D5\u05D5\u05D4",
      "cmp_ZipCode": null,
      "cmp_Phone": "Phone5062",
      "cmp_Responsible": "cmp_Responsible5062",
      "cmp_Fax": null,
      "cmp_AFM": null,
      "cmp_DUNSNumber": null,
      "cmp_LastUpdateTime": "2024-04-18T19:17:03.2270000"
    },
    {
      "dep_ID": 122,
      "dep_Code": "ENP",
      "cmp_FullName": "cmp_FullName5063",
      "cmp_Address": null,
      "cmp_City": "\u05D0\u05D9\u05D9\u05E8\u05E4\u05D5\u05E8\u05D8 \u05E1\u05D9\u05D8\u05D9",
      "cmp_ZipCode": null,
      "cmp_Phone": "Phone5063",
      "cmp_Responsible": "cmp_Responsible5063",
      "cmp_Fax": null,
      "cmp_AFM": null,
      "cmp_DUNSNumber": null,
      "cmp_LastUpdateTime": "2024-04-21T14:08:47.3030000"
    },
    {
      "dep_ID": 123,
      "dep_Code": "RONT",
      "cmp_FullName": "cmp_FullName5065",
      "cmp_Address": "\u05D4\u05DB\u05D9\u05E9\u05D5\u05E8 49",
      "cmp_City": "\u05D7\u05D5\u05DC\u05D5\u05DF",
      "cmp_ZipCode": null,
      "cmp_Phone": "Phone5065",
      "cmp_Responsible": "cmp_Responsible5065",
      "cmp_Fax": null,
      "cmp_AFM": null,
      "cmp_DUNSNumber": null,
      "cmp_LastUpdateTime": "2024-05-30T13:51:14.4070000"
    },
    {
      "dep_ID": 124,
      "dep_Code": "UTRM",
      "cmp_FullName": "cmp_FullName5066",
      "cmp_Address": null,
      "cmp_City": null,
      "cmp_ZipCode": null,
      "cmp_Phone": "Phone5066",
      "cmp_Responsible": "cmp_Responsible5066",
      "cmp_Fax": null,
      "cmp_AFM": null,
      "cmp_DUNSNumber": null,
      "cmp_LastUpdateTime": "2024-06-02T16:58:25.4270000"
    },
    {
      "dep_ID": 125,
      "dep_Code": "AVT",
      "cmp_FullName": "cmp_FullName5067",
      "cmp_Address": "\u05D2\u05E8\u05E0\u05D3\u05D5\u05E1 4 ",
      "cmp_City": "\u05E8\u05DE\u05EA \u05D2\u05DF",
      "cmp_ZipCode": null,
      "cmp_Phone": "Phone5067",
      "cmp_Responsible": "cmp_Responsible5067",
      "cmp_Fax": null,
      "cmp_AFM": null,
      "cmp_DUNSNumber": null,
      "cmp_LastUpdateTime": "2024-06-05T15:46:15.0700000"
    },
    {
      "dep_ID": 126,
      "dep_Code": "UDC",
      "cmp_FullName": "cmp_FullName5068",
      "cmp_Address": "\u05D4\u05DB\u05D9\u05E9\u05D5\u05E8 30",
      "cmp_City": "\u05D7\u05D5\u05DC\u05D5\u05DF",
      "cmp_ZipCode": null,
      "cmp_Phone": "Phone5068",
      "cmp_Responsible": "cmp_Responsible5068",
      "cmp_Fax": null,
      "cmp_AFM": null,
      "cmp_DUNSNumber": "516085420",
      "cmp_LastUpdateTime": "2024-06-09T19:46:23.7730000"
    },
    {
      "dep_ID": 127,
      "dep_Code": "DAR",
      "cmp_FullName": "cmp_FullName5069",
      "cmp_Address": "\u05D4\u05E8\u05E6\u05DC 42",
      "cmp_City": "\u05DB\u05E4\u05E8 \u05E1\u05D1\u05D0",
      "cmp_ZipCode": null,
      "cmp_Phone": "Phone5069",
      "cmp_Responsible": "cmp_Responsible5069",
      "cmp_Fax": null,
      "cmp_AFM": null,
      "cmp_DUNSNumber": null,
      "cmp_LastUpdateTime": "2024-06-10T09:56:11.7900000"
    },
    {
      "dep_ID": 128,
      "dep_Code": "YKI",
      "cmp_FullName": "cmp_FullName5070",
      "cmp_Address": "\u05E1\u05D5\u05E7\u05D5\u05DC\u05D5\u05D1 9",
      "cmp_City": "\u05E8\u05DE\u05EA \u05D2\u05DF",
      "cmp_ZipCode": null,
      "cmp_Phone": "Phone5070",
      "cmp_Responsible": "cmp_Responsible5070",
      "cmp_Fax": null,
      "cmp_AFM": null,
      "cmp_DUNSNumber": null,
      "cmp_LastUpdateTime": "2024-07-07T16:04:18.4700000"
    },
    {
      "dep_ID": 129,
      "dep_Code": "RAN",
      "cmp_FullName": "cmp_FullName5071",
      "cmp_Address": null,
      "cmp_City": "\u05D0\u05E9\u05D3\u05D5\u05D3",
      "cmp_ZipCode": null,
      "cmp_Phone": "Phone5071",
      "cmp_Responsible": "cmp_Responsible5071",
      "cmp_Fax": null,
      "cmp_AFM": null,
      "cmp_DUNSNumber": null,
      "cmp_LastUpdateTime": "2024-07-15T11:11:11.7370000"
    },
    {
      "dep_ID": 130,
      "dep_Code": "LHB",
      "cmp_FullName": "cmp_FullName5072",
      "cmp_Address": "\u05D4\u05DE\u05E9\u05D1\u05D9\u05E8 1 \u05D7\u05D5\u05DC\u05D5\u05DF",
      "cmp_City": "\u05D7\u05D5\u05DC\u05D5\u05DF",
      "cmp_ZipCode": null,
      "cmp_Phone": "Phone5072",
      "cmp_Responsible": "cmp_Responsible5072",
      "cmp_Fax": null,
      "cmp_AFM": null,
      "cmp_DUNSNumber": "510058977",
      "cmp_LastUpdateTime": "2024-07-15T13:13:28.7370000"
    },
    {
      "dep_ID": 131,
      "dep_Code": "AVIT",
      "cmp_FullName": "cmp_FullName5074",
      "cmp_Address": "\u05D4\u05E0\u05D2\u05E8 24",
      "cmp_City": "\u05D4\u05D5\u05D3 \u05D4\u05E9\u05E8\u05D5\u05DF",
      "cmp_ZipCode": null,
      "cmp_Phone": "Phone5074",
      "cmp_Responsible": "cmp_Responsible5074",
      "cmp_Fax": null,
      "cmp_AFM": null,
      "cmp_DUNSNumber": null,
      "cmp_LastUpdateTime": "2024-08-25T11:44:08.8730000"
    },
    {
      "dep_ID": 132,
      "dep_Code": "AVI",
      "cmp_FullName": "cmp_FullName5075",
      "cmp_Address": "\u05D4\u05E0\u05D2\u05E8 24",
      "cmp_City": "\u05D4\u05D5\u05D3 \u05D4\u05E9\u05E8\u05D5\u05DF",
      "cmp_ZipCode": null,
      "cmp_Phone": "Phone5075",
      "cmp_Responsible": "cmp_Responsible5075",
      "cmp_Fax": null,
      "cmp_AFM": null,
      "cmp_DUNSNumber": null,
      "cmp_LastUpdateTime": "2024-08-25T11:43:17.6030000"
    },
    {
      "dep_ID": 133,
      "dep_Code": "LIK",
      "cmp_FullName": "cmp_FullName5076",
      "cmp_Address": "\u05E9\u05D1\u05D5 3 ",
      "cmp_City": "\u05D2\u05D3\u05E8\u05D4 ",
      "cmp_ZipCode": null,
      "cmp_Phone": "Phone5076",
      "cmp_Responsible": "cmp_Responsible5076",
      "cmp_Fax": null,
      "cmp_AFM": null,
      "cmp_DUNSNumber": null,
      "cmp_LastUpdateTime": "2024-08-18T16:49:12.2930000"
    },
    {
      "dep_ID": 134,
      "dep_Code": "YDD",
      "cmp_FullName": "cmp_FullName5077",
      "cmp_Address": "\u05DE\u05D2\u05D3\u05DC\u05D9 \u05D1\u05E1\u05E8 \u05E4\u05EA\u05D7 \u05EA\u05E7\u05D5\u05D5\u05D4 \u05DE\u05D2\u05D3\u05DC Y",
      "cmp_City": "\u05E4\u05EA\u05D7 \u05EA\u05E7\u05D5\u05D5\u05D4",
      "cmp_ZipCode": null,
      "cmp_Phone": "Phone5077",
      "cmp_Responsible": "cmp_Responsible5077",
      "cmp_Fax": null,
      "cmp_AFM": null,
      "cmp_DUNSNumber": null,
      "cmp_LastUpdateTime": "2024-08-21T17:56:05.6500000"
    },
    {
      "dep_ID": 135,
      "dep_Code": "GDAT",
      "cmp_FullName": "cmp_FullName5078",
      "cmp_Address": "\u05E8\u05D9\u05D1\u0022\u05DC 9",
      "cmp_City": "\u05EA\u05DC \u05D0\u05D1\u05D9\u05D1",
      "cmp_ZipCode": null,
      "cmp_Phone": "Phone5078",
      "cmp_Responsible": "cmp_Responsible5078",
      "cmp_Fax": null,
      "cmp_AFM": null,
      "cmp_DUNSNumber": null,
      "cmp_LastUpdateTime": "2024-09-04T11:15:35.7670000"
    },
    {
      "dep_ID": 136,
      "dep_Code": "DIO",
      "cmp_FullName": "cmp_FullName5079",
      "cmp_Address": null,
      "cmp_City": null,
      "cmp_ZipCode": null,
      "cmp_Phone": "Phone5079",
      "cmp_Responsible": "cmp_Responsible5079",
      "cmp_Fax": null,
      "cmp_AFM": null,
      "cmp_DUNSNumber": null,
      "cmp_LastUpdateTime": "2024-08-29T15:00:52.1800000"
    },
    {
      "dep_ID": 137,
      "dep_Code": "CAG",
      "cmp_FullName": "cmp_FullName5080",
      "cmp_Address": null,
      "cmp_City": null,
      "cmp_ZipCode": null,
      "cmp_Phone": "Phone5080",
      "cmp_Responsible": "cmp_Responsible5080",
      "cmp_Fax": null,
      "cmp_AFM": null,
      "cmp_DUNSNumber": null,
      "cmp_LastUpdateTime": "2024-08-29T15:33:20.2000000"
    },
    {
      "dep_ID": 138,
      "dep_Code": "GDAK",
      "cmp_FullName": "cmp_FullName5081",
      "cmp_Address": "\u05D4\u05DB\u05E8\u05DD 6",
      "cmp_City": "\u05E7\u05E6\u05E8\u05D9\u05DF",
      "cmp_ZipCode": null,
      "cmp_Phone": "Phone5081",
      "cmp_Responsible": "cmp_Responsible5081",
      "cmp_Fax": null,
      "cmp_AFM": null,
      "cmp_DUNSNumber": null,
      "cmp_LastUpdateTime": "2024-09-04T11:16:30.5330000"
    },
    {
      "dep_ID": 139,
      "dep_Code": "WVZ",
      "cmp_FullName": "cmp_FullName5082",
      "cmp_Address": "\u05E9\u05E8\u05D5\u05DF 3 \u05E7\u05E8\u05D9\u05EA \u05EA\u05E2\u05D5\u05E4\u05D4",
      "cmp_City": "\u05E7\u05E8\u05D9\u05EA \u05EA\u05E2\u05D5\u05E4\u05D4",
      "cmp_ZipCode": null,
      "cmp_Phone": "Phone5082",
      "cmp_Responsible": "cmp_Responsible5082",
      "cmp_Fax": null,
      "cmp_AFM": null,
      "cmp_DUNSNumber": "516833365",
      "cmp_LastUpdateTime": "2024-10-15T20:27:02.4070000"
    },
    {
      "dep_ID": 140,
      "dep_Code": "ADR",
      "cmp_FullName": "cmp_FullName5083",
      "cmp_Address": "\u05D3\u05D5\u05D3 \u05E4\u05E0\u05E7\u05E1 10",
      "cmp_City": "\u05E0\u05EA\u05E0\u05D9\u05D4",
      "cmp_ZipCode": null,
      "cmp_Phone": "Phone5083",
      "cmp_Responsible": "cmp_Responsible5083",
      "cmp_Fax": null,
      "cmp_AFM": null,
      "cmp_DUNSNumber": null,
      "cmp_LastUpdateTime": "2024-10-27T18:09:56.3530000"
    },
    {
      "dep_ID": 141,
      "dep_Code": "NAR",
      "cmp_FullName": "cmp_FullName5084",
      "cmp_Address": null,
      "cmp_City": null,
      "cmp_ZipCode": null,
      "cmp_Phone": "Phone5084",
      "cmp_Responsible": "cmp_Responsible5084",
      "cmp_Fax": null,
      "cmp_AFM": null,
      "cmp_DUNSNumber": null,
      "cmp_LastUpdateTime": "2024-11-20T18:03:21.6370000"
    },
    {
      "dep_ID": 142,
      "dep_Code": "MIK",
      "cmp_FullName": "cmp_FullName5085",
      "cmp_Address": "\u05D0\u05D4\u05D5\u05D3 \u05E7\u05D9\u05E0\u05DE\u05D5\u05DF 3 ",
      "cmp_City": "\u05D1\u05EA \u05D9\u05DD",
      "cmp_ZipCode": null,
      "cmp_Phone": "Phone5085",
      "cmp_Responsible": "cmp_Responsible5085",
      "cmp_Fax": null,
      "cmp_AFM": null,
      "cmp_DUNSNumber": null,
      "cmp_LastUpdateTime": "2024-10-31T18:15:55.8030000"
    },
    {
      "dep_ID": 143,
      "dep_Code": "NIC",
      "cmp_FullName": "cmp_FullName5086",
      "cmp_Address": "\u05D0\u05D3\u05D5\u05DD 26",
      "cmp_City": "\u05DB\u05E0\u05D5\u05EA",
      "cmp_ZipCode": null,
      "cmp_Phone": "Phone5086",
      "cmp_Responsible": "cmp_Responsible5086",
      "cmp_Fax": null,
      "cmp_AFM": null,
      "cmp_DUNSNumber": null,
      "cmp_LastUpdateTime": "2024-11-12T17:35:06.0570000"
    },
    {
      "dep_ID": 144,
      "dep_Code": "YST",
      "cmp_FullName": "cmp_FullName5087",
      "cmp_Address": null,
      "cmp_City": "\u05E7\u05E8\u05D9\u05EA \u05D2\u05EA",
      "cmp_ZipCode": null,
      "cmp_Phone": "Phone5087",
      "cmp_Responsible": "cmp_Responsible5087",
      "cmp_Fax": null,
      "cmp_AFM": null,
      "cmp_DUNSNumber": null,
      "cmp_LastUpdateTime": "2024-11-20T10:53:32.5400000"
    },
    {
      "dep_ID": 145,
      "dep_Code": "DRW",
      "cmp_FullName": "cmp_FullName5088",
      "cmp_Address": "\u05D4\u05D0\u05D9\u05DC\u05DF 29 ",
      "cmp_City": "\u05D0\u05D5\u05E8 \u05E2\u05E7\u05D9\u05D1\u05D0",
      "cmp_ZipCode": null,
      "cmp_Phone": "Phone5088",
      "cmp_Responsible": "cmp_Responsible5088",
      "cmp_Fax": null,
      "cmp_AFM": null,
      "cmp_DUNSNumber": null,
      "cmp_LastUpdateTime": "2024-12-16T10:47:34.5400000"
    },
    {
      "dep_ID": 146,
      "dep_Code": "ORE",
      "cmp_FullName": "cmp_FullName5089",
      "cmp_Address": "\u05D4\u05E9\u05D5\u05E0\u05D9\u05EA 2",
      "cmp_City": "\u05D4\u05E8\u05E6\u05DC\u05D9\u05D4",
      "cmp_ZipCode": null,
      "cmp_Phone": "Phone5089",
      "cmp_Responsible": "cmp_Responsible5089",
      "cmp_Fax": null,
      "cmp_AFM": null,
      "cmp_DUNSNumber": null,
      "cmp_LastUpdateTime": "2024-12-17T11:13:35.4000000"
    },
    {
      "dep_ID": 147,
      "dep_Code": "AMD",
      "cmp_FullName": "cmp_FullName5090",
      "cmp_Address": "\u05D3\u05E8\u05DA \u05D4\u05E9\u05D3\u05D5\u05EA 38 \u05D1 ",
      "cmp_City": "\u05DB\u05E4\u05E8 \u05E9\u05DE\u05E8\u05D9\u05D4\u05D5",
      "cmp_ZipCode": null,
      "cmp_Phone": "Phone5090",
      "cmp_Responsible": "cmp_Responsible5090",
      "cmp_Fax": null,
      "cmp_AFM": null,
      "cmp_DUNSNumber": null,
      "cmp_LastUpdateTime": "2024-12-18T12:29:31.1270000"
    },
    {
      "dep_ID": 148,
      "dep_Code": "INT",
      "cmp_FullName": "cmp_FullName5091",
      "cmp_Address": "\u05D4\u05D0\u05D2\u05D5\u05D6 10 \u05D0.\u05EA. \u05DE\u05D5\u05D3\u05D9\u05E2\u05D9\u05DF",
      "cmp_City": null,
      "cmp_ZipCode": null,
      "cmp_Phone": "Phone5091",
      "cmp_Responsible": "cmp_Responsible5091",
      "cmp_Fax": null,
      "cmp_AFM": null,
      "cmp_DUNSNumber": null,
      "cmp_LastUpdateTime": "2024-12-23T11:02:14.6370000"
    },
    {
      "dep_ID": 149,
      "dep_Code": "YAT",
      "cmp_FullName": "cmp_FullName5092",
      "cmp_Address": "\u05D4\u05D7\u05E8\u05DE\u05D5\u05DF 7",
      "cmp_City": "\u05D9\u05D1\u05E0\u05D4",
      "cmp_ZipCode": null,
      "cmp_Phone": "Phone5092",
      "cmp_Responsible": "cmp_Responsible5092",
      "cmp_Fax": null,
      "cmp_AFM": null,
      "cmp_DUNSNumber": null,
      "cmp_LastUpdateTime": "2025-01-01T14:24:23.5400000"
    },
    {
      "dep_ID": 150,
      "dep_Code": "BEE",
      "cmp_FullName": "cmp_FullName5093",
      "cmp_Address": null,
      "cmp_City": null,
      "cmp_ZipCode": null,
      "cmp_Phone": "Phone5093",
      "cmp_Responsible": "cmp_Responsible5093",
      "cmp_Fax": null,
      "cmp_AFM": null,
      "cmp_DUNSNumber": null,
      "cmp_LastUpdateTime": "2025-01-02T11:18:59.1130000"
    },
    {
      "dep_ID": 151,
      "dep_Code": "ALB",
      "cmp_FullName": "cmp_FullName5094",
      "cmp_Address": "\u05E8\u05D1 \u05D0\u05E9\u05D9 6 ",
      "cmp_City": "\u05EA\u05DC \u05D0\u05D1\u05D9\u05D1",
      "cmp_ZipCode": null,
      "cmp_Phone": "Phone5094",
      "cmp_Responsible": "cmp_Responsible5094",
      "cmp_Fax": null,
      "cmp_AFM": null,
      "cmp_DUNSNumber": null,
      "cmp_LastUpdateTime": "2025-01-19T10:15:43.0600000"
    },
    {
      "dep_ID": 152,
      "dep_Code": "BUL",
      "cmp_FullName": "cmp_FullName5095",
      "cmp_Address": "\u05D9\u05D3 \u05D7\u05E8\u05D5\u05E6\u05D9\u05DD 16 ",
      "cmp_City": "\u05D9\u05E8\u05D5\u05E9\u05DC\u05D9\u05DD",
      "cmp_ZipCode": null,
      "cmp_Phone": "Phone5095",
      "cmp_Responsible": "cmp_Responsible5095",
      "cmp_Fax": null,
      "cmp_AFM": null,
      "cmp_DUNSNumber": null,
      "cmp_LastUpdateTime": "2025-02-24T15:51:04.6800000"
    },
    {
      "dep_ID": 153,
      "dep_Code": "YOC",
      "cmp_FullName": "cmp_FullName5096",
      "cmp_Address": "\u05D4\u05D2\u05D3\u05D5\u05D3 \u05D4\u05E2\u05D1\u05E8\u05D9 32 ",
      "cmp_City": "\u05EA\u05DC \u05D0\u05D1\u05D9\u05D1",
      "cmp_ZipCode": null,
      "cmp_Phone": "Phone5096",
      "cmp_Responsible": "cmp_Responsible5096",
      "cmp_Fax": null,
      "cmp_AFM": null,
      "cmp_DUNSNumber": null,
      "cmp_LastUpdateTime": "2025-03-02T12:55:57.4370000"
    },
    {
      "dep_ID": 154,
      "dep_Code": "EIZ",
      "cmp_FullName": "cmp_FullName5097",
      "cmp_Address": null,
      "cmp_City": null,
      "cmp_ZipCode": null,
      "cmp_Phone": "Phone5097",
      "cmp_Responsible": "cmp_Responsible5097",
      "cmp_Fax": null,
      "cmp_AFM": null,
      "cmp_DUNSNumber": null,
      "cmp_LastUpdateTime": "2025-03-27T14:49:06.0700000"
    },
    {
      "dep_ID": 155,
      "dep_Code": "NWISH",
      "cmp_FullName": "cmp_FullName5098",
      "cmp_Address": null,
      "cmp_City": null,
      "cmp_ZipCode": null,
      "cmp_Phone": "Phone5098",
      "cmp_Responsible": "cmp_Responsible5098",
      "cmp_Fax": null,
      "cmp_AFM": null,
      "cmp_DUNSNumber": null,
      "cmp_LastUpdateTime": "2025-03-28T09:47:08.3630000"
    },
    {
      "dep_ID": 156,
      "dep_Code": "DGS",
      "cmp_FullName": "cmp_FullName5099",
      "cmp_Address": "\u05E9\u05E9\u05EA \u05D4\u05D9\u05DE\u05D9\u05DD 23",
      "cmp_City": "\u05D9\u05D4\u05D5\u05D3",
      "cmp_ZipCode": null,
      "cmp_Phone": "Phone5099",
      "cmp_Responsible": "cmp_Responsible5099",
      "cmp_Fax": null,
      "cmp_AFM": null,
      "cmp_DUNSNumber": null,
      "cmp_LastUpdateTime": "2025-03-28T09:57:43.6900000"
    },
    {
      "dep_ID": 157,
      "dep_Code": "SER",
      "cmp_FullName": "cmp_FullName5100",
      "cmp_Address": "\u05D0\u05DC\u05D9\u05E2\u05D6\u05E8 \u05D1\u05DF \u05D9\u05D4\u05D5\u05D3\u05D4 5",
      "cmp_City": "\u05E0\u05EA\u05E0\u05D9\u05D4",
      "cmp_ZipCode": null,
      "cmp_Phone": "Phone5100",
      "cmp_Responsible": "cmp_Responsible5100",
      "cmp_Fax": null,
      "cmp_AFM": null,
      "cmp_DUNSNumber": null,
      "cmp_LastUpdateTime": "2025-03-30T12:31:21.7770000"
    },
    {
      "dep_ID": 158,
      "dep_Code": "INFR",
      "cmp_FullName": "cmp_FullName5101",
      "cmp_Address": "\u05D8\u05E9\u05E8\u05E0\u05D9\u05D7\u05D5\u05D1\u05E1\u05E7\u05D9 24",
      "cmp_City": "\u05DB\u05E4\u05E8 \u05E1\u05D1\u05D0",
      "cmp_ZipCode": null,
      "cmp_Phone": "Phone5101",
      "cmp_Responsible": "cmp_Responsible5101",
      "cmp_Fax": null,
      "cmp_AFM": null,
      "cmp_DUNSNumber": null,
      "cmp_LastUpdateTime": "2025-04-23T15:14:28.2970000"
    },
    {
      "dep_ID": 159,
      "dep_Code": "TIT",
      "cmp_FullName": "cmp_FullName5102",
      "cmp_Address": "\u05D3\u05D5\u05D3\u05D5 \u05D3\u05D5\u05EA\u05DF  5/35 ",
      "cmp_City": "\u05E8\u05D0\u05E9\u05D5\u05DF \u05DC\u05E6\u05D9\u05D5\u05DF  ",
      "cmp_ZipCode": null,
      "cmp_Phone": "Phone5102",
      "cmp_Responsible": "cmp_Responsible5102",
      "cmp_Fax": null,
      "cmp_AFM": null,
      "cmp_DUNSNumber": null,
      "cmp_LastUpdateTime": "2025-05-13T10:56:06.0530000"
    },
    {
      "dep_ID": 160,
      "dep_Code": "NSTS",
      "cmp_FullName": "cmp_FullName5103",
      "cmp_Address": null,
      "cmp_City": null,
      "cmp_ZipCode": null,
      "cmp_Phone": "Phone5103",
      "cmp_Responsible": "cmp_Responsible5103",
      "cmp_Fax": null,
      "cmp_AFM": null,
      "cmp_DUNSNumber": null,
      "cmp_LastUpdateTime": "2025-05-19T13:38:36.1230000"
    }
  ]
}